mgui/__init__.py
mgui/py.typed
mgui-0.0.1rc0.dist-info/LICENSE
mgui-0.0.1rc0.dist-info/METADATA
mgui-0.0.1rc0.dist-info/WHEEL
mgui-0.0.1rc0.dist-info/top_level.txt
mgui-0.0.1rc0.dist-info/RECORD
